simple_config.py
simple_config-1.0.1.dist-info/DESCRIPTION.rst
simple_config-1.0.1.dist-info/METADATA
simple_config-1.0.1.dist-info/RECORD
simple_config-1.0.1.dist-info/WHEEL
simple_config-1.0.1.dist-info/metadata.json
simple_config-1.0.1.dist-info/top_level.txt
