Metadata-Version: 2.0
Name: simple-config
Version: 1.0.1
Summary: A simple configuration file manager for python
Home-page: https://github.com/poudel/simple-config
Author: keshaB Paudel
Author-email: self@keshab.net
License: MIT
Keywords: config json-config user-config
Platform: UNKNOWN
Classifier: Development Status :: 4 - Beta
Classifier: Intended Audience :: Developers
Classifier: Topic :: Software Development :: Build Tools
Classifier: License :: OSI Approved :: MIT License
Classifier: Programming Language :: Python
Classifier: Programming Language :: Python :: 3
Classifier: Programming Language :: Python :: 3.6
Classifier: Programming Language :: Python :: Implementation :: CPython
